README.rst
setup.py
TextFileSizeChecker/__init__.py
TextFileSizeChecker/txt_file_size_checker.py
TextFile_SizeChecker.egg-info/PKG-INFO
TextFile_SizeChecker.egg-info/SOURCES.txt
TextFile_SizeChecker.egg-info/dependency_links.txt
TextFile_SizeChecker.egg-info/entry_points.txt
TextFile_SizeChecker.egg-info/top_level.txt