Metadata-Version: 2.1
Name: TextFile-SizeChecker
Version: 0.3
Summary: Calculate the number of lines, words and characters in a text file
Home-page: https://github.com/urosjevremovic/txt-file-size-checker
Author: Uros Jevremovic
Author-email: jevremovic.uros91@gmail.com
License: MIT
Platform: UNKNOWN
